ltc_client/__init__.py
ltc_client/api.py
ltc_client/geometry_api.py
ltc_client/helpers.py
ltc_client/job.py
ltc_client/material.py
ltc_client/winding_api.py
ltc_client/worker.py
ltc_client-0.2.61.dist-info/METADATA
ltc_client-0.2.61.dist-info/WHEEL
ltc_client-0.2.61.dist-info/licenses/LICENSE
ltc_client-0.2.61.dist-info/RECORD
