Metadata-Version: 2.4
Name: ltc-client
Version: 0.2.61
Summary: Client and Worker module for Tin Arm Engineering LTC service
License: MIT
License-File: LICENSE
Author: Martin West
Author-email: martin@tinarmengineering.com
Requires-Python: >=3.9
Classifier: Programming Language :: Python :: 3
Classifier: License :: OSI Approved :: MIT License
Classifier: Operating System :: OS Independent
Requires-Dist: Pint (>=0.24)
Requires-Dist: numpy (>=2.0.2)
Requires-Dist: pika (>=1.3.2)
Requires-Dist: python-logging-rabbitmq (>=2.3.0)
Requires-Dist: requests (>=2.32.3)
Requires-Dist: tqdm (>=4.66.4)
Requires-Dist: urllib3 (>=2.6.3)
Requires-Dist: webstompy (>=0.1.5)
Project-URL: Homepage, https://github.com/TinArmEngineering/ltc_client/
Project-URL: Issues, https://github.com/TinArmEngineering/ltc_client/issues
Project-URL: Repository, https://github.com/TinArmEngineering/ltc_client/
